{"links": {"self": {"href": "data/repositories/osrf/gazebo_design/pullrequests/18/comments/7640427.json"}, "code": {"href": "https://api.bitbucket.org/2.0/repositories/osrf/gazebo_design/diff/osrf/gazebo_design:None..None?path=nested_model%2Fnested_model.md"}, "html": {"href": "#!/osrf/gazebo_design/pull-requests/18/_/diff#comment-7640427"}}, "parent": {"id": 7640256, "links": {"self": {"href": "data/repositories/osrf/gazebo_design/pullrequests/18/comments/7640256.json"}, "html": {"href": "#!/osrf/gazebo_design/pull-requests/18/_/diff#comment-7640256"}}}, "deleted": false, "pullrequest": {"type": "pullrequest", "id": 18, "links": {"self": {"href": "data/repositories/osrf/gazebo_design/pullrequests/18.json"}, "html": {"href": "#!/osrf/gazebo_design/pull-requests/18"}}, "title": "Add support for nested models in Gazebo"}, "content": {"raw": "`recursive` attribute also looks nice. I used the custom `nested_sdf` element as the `copy_data` example is already there and easier to parse and implement.", "markup": "markdown", "html": "<p><code>recursive</code> attribute also looks nice. I used the custom <code>nested_sdf</code> element as the <code>copy_data</code> example is already there and easier to parse and implement.</p>", "type": "rendered"}, "created_on": "2015-06-18T17:54:56.283192+00:00", "user": {"display_name": "Ian Chen", "uuid": "{eaa6fca5-6deb-43f6-907f-971c144735dd}", "links": {"self": {"href": "https://api.bitbucket.org/2.0/users/%7Beaa6fca5-6deb-43f6-907f-971c144735dd%7D"}, "html": {"href": "https://bitbucket.org/%7Beaa6fca5-6deb-43f6-907f-971c144735dd%7D/"}, "avatar": {"href": "https://avatar-management--avatars.us-west-2.prod.public.atl-paas.net/557058:10b01d41-a2e9-4a41-a907-e6e2f03b6cd5/1e4adcdf-1946-4280-9aea-eb5f15a7f912/128"}}, "nickname": "Ian Chen", "type": "user", "account_id": "557058:10b01d41-a2e9-4a41-a907-e6e2f03b6cd5"}, "inline": {"to": null, "from": null, "outdated": false, "path": "nested_model/nested_model.md"}, "updated_on": "2015-06-18T17:55:10.868000+00:00", "type": "pullrequest_comment", "id": 7640427}